CHANGES.txt
MANIFEST.in
README.md
setup.py
src/md/__init__.py
src/md.recipe.celery.egg-info/PKG-INFO
src/md.recipe.celery.egg-info/SOURCES.txt
src/md.recipe.celery.egg-info/dependency_links.txt
src/md.recipe.celery.egg-info/entry_points.txt
src/md.recipe.celery.egg-info/namespace_packages.txt
src/md.recipe.celery.egg-info/not-zip-safe
src/md.recipe.celery.egg-info/requires.txt
src/md.recipe.celery.egg-info/top_level.txt
src/md/recipe/__init__.py
src/md/recipe/celery/README.md
src/md/recipe/celery/__init__.py
src/md/recipe/celery/loader.py
src/md/recipe/celery/tests.py