Metadata-Version: 1.0
Name: md.recipe.celery
Version: 1.1
Summary: Buildout recipe for installing celery for use with Zope's ZCA and configuring it using an ini file.
Home-page: https://github.com/minddistrict/md.recipe.celery
Author: Remco Wendt
Author-email: remco.wendt@gmail.com
License: BSD
Platform: UNKNOWN
Classifier: Framework :: Buildout :: Recipe
Classifier: Intended Audience :: Developers
Classifier: License :: OSI Approved :: BSD License
Classifier: Programming Language :: Python
Classifier: Topic :: Software Development :: Build Tools
Classifier: Topic :: Software Development :: Libraries :: Python Modules
